setup.py
BtoDConverter/BtoDConverter.py
BtoDConverter/__init__.py
BtoDConverter.egg-info/PKG-INFO
BtoDConverter.egg-info/SOURCES.txt
BtoDConverter.egg-info/dependency_links.txt
BtoDConverter.egg-info/requires.txt
BtoDConverter.egg-info/top_level.txt