Metadata-Version: 1.0
Name: BtoDConverter
Version: 0.1
Summary: Converts a binary number to a decimal number
Home-page: none
Author: Sel_iddqd
Author-email: none
License: UNKNOWN
Download-URL: none
Platform: UNKNOWN
